openquake.engine-2.2.0-nspkg.pth
bin/__init__.py
bin/oq
openquake/calculators/__init__.py
openquake/calculators/base.py
openquake/calculators/classical.py
openquake/calculators/classical_bcr.py
openquake/calculators/classical_damage.py
openquake/calculators/classical_risk.py
openquake/calculators/disaggregation.py
openquake/calculators/event_based.py
openquake/calculators/event_based_risk.py
openquake/calculators/reportwriter.py
openquake/calculators/scenario.py
openquake/calculators/scenario_damage.py
openquake/calculators/scenario_risk.py
openquake/calculators/ucerf_classical.py
openquake/calculators/ucerf_event_based.py
openquake/calculators/views.py
openquake/calculators/export/__init__.py
openquake/calculators/export/hazard.py
openquake/calculators/export/risk.py
openquake/calculators/tests/__init__.py
openquake/calculators/tests/base_test.py
openquake/calculators/tests/classical_bcr_test.py
openquake/calculators/tests/classical_damage_test.py
openquake/calculators/tests/classical_risk_test.py
openquake/calculators/tests/classical_test.py
openquake/calculators/tests/classical_tiling_test.py
openquake/calculators/tests/disagg_test.py
openquake/calculators/tests/event_based_risk_test.py
openquake/calculators/tests/event_based_test.py
openquake/calculators/tests/expected_gmf.csv
openquake/calculators/tests/scenario_damage_test.py
openquake/calculators/tests/scenario_risk_test.py
openquake/calculators/tests/scenario_test.py
openquake/calculators/tests/ucerf_test.py
openquake/commands/__init__.py
openquake/commands/__main__.py
openquake/commands/db.py
openquake/commands/dbserver.py
openquake/commands/engine.py
openquake/commands/export.py
openquake/commands/from_shapefile.py
openquake/commands/info.py
openquake/commands/plot.py
openquake/commands/plot_agg_curve.py
openquake/commands/plot_lc.py
openquake/commands/plot_sites.py
openquake/commands/plot_uhs.py
openquake/commands/purge.py
openquake/commands/reduce.py
openquake.engine-2.2.0.dist-info/DESCRIPTION.rst
openquake.engine-2.2.0.dist-info/LICENSE.txt
openquake.engine-2.2.0.dist-info/METADATA
openquake.engine-2.2.0.dist-info/RECORD
openquake.engine-2.2.0.dist-info/WHEEL
openquake.engine-2.2.0.dist-info/metadata.json
openquake.engine-2.2.0.dist-info/namespace_packages.txt
openquake.engine-2.2.0.dist-info/top_level.txt
