Metadata-Version: 2.0
Name: openquake.engine
Version: 2.2.0
Summary: Computes earthquake hazard and risk.
Home-page: https://github.com/gem/oq-engine
Author: GEM Foundation
Author-email: devops@openquake.org
License: AGPL3
Keywords: earthquake seismic hazard risk
Platform: UNKNOWN
Classifier: Development Status :: 5 - Production/Stable
Classifier: Intended Audience :: Education
Classifier: Intended Audience :: Science/Research
Classifier: Programming Language :: Python :: 2
Classifier: Programming Language :: Python :: 2.7
Classifier: Programming Language :: Python :: 3
Classifier: Programming Language :: Python :: 3.5
Classifier: License :: OSI Approved :: GNU Affero General Public License v3
Classifier: Operating System :: OS Independent
Classifier: Topic :: Scientific/Engineering
Classifier: Environment :: Console
Classifier: Environment :: Web Environment
Requires-Dist: decorator (<4.1,>=3.4)
Requires-Dist: django (<1.11,>=1.6)
Requires-Dist: docutils (<0.14,>=0.11)
Requires-Dist: futures (<3.1,>=2.1)
Requires-Dist: h5py (>=2.2,<2.7)
Requires-Dist: mock (>=1.0,<1.4)
Requires-Dist: nose (>=1.3,<1.4)
Requires-Dist: numpy (>=1.8,<1.12)
Requires-Dist: openquake.hazardlib (==0.22)
Requires-Dist: psutil (>=1.2,<4.5)
Requires-Dist: pyshp (<1.2.11,>=1.2.3)
Requires-Dist: requests (>=2.2,<2.13)
Requires-Dist: scipy (>=0.13,<0.18)
Requires-Dist: shapely (>=1.3,<1.6)
Provides-Extra: celery
Requires-Dist: celery (>=3.1,<4.0); extra == 'celery'
Provides-Extra: plotting
Requires-Dist: matplotlib (>=1.5); extra == 'plotting'
Provides-Extra: rtree
Requires-Dist: Rtree (<0.8.4,>=0.8.2); extra == 'rtree'
